pydirectus/__init__.py
pydirectus/collection.py
pydirectus/collection_test.py
pydirectus/directus.py
pydirectus/field.py
pydirectus/file.py
pydirectus/folder.py
pydirectus/query.py
pydirectus/query_test.py
pydirectus/session.py
pydirectus/session_test.py
pydirectus/test_fixtures.py
pydirectus/translation.py
pydirectus/typing.py
pydirectus_sdk-0.3.1.dist-info/LICENSE
pydirectus_sdk-0.3.1.dist-info/METADATA
pydirectus_sdk-0.3.1.dist-info/WHEEL
pydirectus_sdk-0.3.1.dist-info/top_level.txt
pydirectus_sdk-0.3.1.dist-info/RECORD
