Metadata-Version: 2.2
Name: pydirectus-sdk
Version: 0.3.1
Summary: Python SDK for Directus
Requires-Python: >=3.8
License-File: LICENSE
Requires-Dist: httpx>=0.27.2
Requires-Dist: python-dotenv>=1.0.1
Requires-Dist: rich>=13.8.1
Requires-Dist: tenacity>=9.0.0
